remotedata.py
remotedata-0.1.0.dist-info/entry_points.txt
remotedata-0.1.0.dist-info/WHEEL
remotedata-0.1.0.dist-info/METADATA
remotedata-0.1.0.dist-info/RECORD
